{
	"format_version": "1.12.0",
	"minecraft:geometry": [
		{
			"description": {
				"identifier": "geometry.mossy01",
				"texture_width": 64,
				"texture_height": 64,
				"visible_bounds_width": 2,
				"visible_bounds_height": 2.5,
				"visible_bounds_offset": [0, 0.75, 0]
			},
			"bones": [
				{
					"name": "bone",
					"pivot": [0, 0, 0],
					"cubes": [
						{
							"origin": [-6, 9, -6],
							"size": [12, 3, 12],
							"uv": {
								"north": {"uv": [12.06, 0.06], "uv_size": [11.88, 2.88]},
								"east": {"uv": [12.06, 3.06], "uv_size": [11.88, 2.88]},
								"south": {"uv": [12.06, 6.06], "uv_size": [11.88, 2.88]},
								"west": {"uv": [12.06, 9.06], "uv_size": [11.88, 2.88]},
								"up": {"uv": [0.06, 0.06], "uv_size": [11.88, 11.88]},
								"down": {"uv": [0.06, 23.94], "uv_size": [11.88, -11.88]}
							}
						},
						{
							"origin": [-3.6, 2, -4.5],
							"size": [7.2, 2, 2],
							"uv": {
								"north": {"uv": [24.06, 10.06], "uv_size": [6.88, 1.88]},
								"east": {"uv": [28.06, 28.06], "uv_size": [1.88, 1.88]},
								"south": {"uv": [24.06, 12.06], "uv_size": [6.88, 1.88]},
								"west": {"uv": [30.06, 2.06], "uv_size": [1.88, 1.88]},
								"up": {"uv": [24.06, 14.06], "uv_size": [6.88, 1.88]},
								"down": {"uv": [24.06, 17.94], "uv_size": [6.88, -1.88]}
							}
						},
						{
							"origin": [-3.6, 2, 2.5],
							"size": [7.2, 2, 2],
							"uv": {
								"north": {"uv": [24.06, 18.06], "uv_size": [6.88, 1.88]},
								"east": {"uv": [30.06, 4.06], "uv_size": [1.88, 1.88]},
								"south": {"uv": [24.06, 20.06], "uv_size": [6.88, 1.88]},
								"west": {"uv": [30.06, 6.06], "uv_size": [1.88, 1.88]},
								"up": {"uv": [24.06, 22.06], "uv_size": [6.88, 1.88]},
								"down": {"uv": [24.06, 25.94], "uv_size": [6.88, -1.88]}
							}
						},
						{
							"origin": [-1, 2, -2.5],
							"size": [2, 2, 5],
							"uv": {
								"north": {"uv": [8.06, 30.06], "uv_size": [1.88, 1.88]},
								"east": {"uv": [6.06, 24.06], "uv_size": [4.88, 1.88]},
								"south": {"uv": [30.06, 8.06], "uv_size": [1.88, 1.88]},
								"west": {"uv": [26.06, 0.06], "uv_size": [4.88, 1.88]},
								"up": {"uv": [26.06, 2.06], "uv_size": [1.88, 4.88]},
								"down": {"uv": [6.06, 30.94], "uv_size": [1.88, -4.88]}
							}
						},
						{
							"origin": [-0.87663, -1.826, -6.81871],
							"size": [2, 9.8, 2],
							"pivot": [0, 0, 0],
							"rotation": [-20, 47.5, 0],
							"uv": {
								"north": {"uv": [12.06, 12.06], "uv_size": [1.88, 9.88]},
								"east": {"uv": [14.06, 12.06], "uv_size": [1.88, 9.88]},
								"south": {"uv": [16.06, 12.06], "uv_size": [1.88, 9.88]},
								"west": {"uv": [18.06, 12.06], "uv_size": [1.88, 9.88]},
								"up": {"uv": [26.06, 7.06], "uv_size": [1.88, 1.88]},
								"down": {"uv": [8.06, 27.94], "uv_size": [1.88, -1.88]}
							}
						},
						{
							"origin": [-0.37663, -4.91218, -6.87274],
							"size": [1, 0.8, 1],
							"pivot": [0, 0, 0],
							"rotation": [-75, 47.5, 0],
							"uv": {
								"north": {"uv": [28.06, 30.06], "uv_size": [0.88, 0.88]},
								"east": {"uv": [29.06, 30.06], "uv_size": [0.88, 0.88]},
								"south": {"uv": [30.06, 29.06], "uv_size": [0.88, 0.88]},
								"west": {"uv": [30.06, 30.06], "uv_size": [0.88, 0.88]},
								"up": {"uv": [31.06, 0.06], "uv_size": [0.88, 0.88]},
								"down": {"uv": [31.06, 1.94], "uv_size": [0.88, -0.88]}
							}
						},
						{
							"origin": [-0.37663, -2.91886, -7.07805],
							"size": [1, 0.8, 1],
							"pivot": [0, 0, 0],
							"rotation": [-57.5, 47.5, 0],
							"uv": {
								"north": {"uv": [31.06, 11.06], "uv_size": [0.88, 0.88]},
								"east": {"uv": [31.06, 12.06], "uv_size": [0.88, 0.88]},
								"south": {"uv": [31.06, 13.06], "uv_size": [0.88, 0.88]},
								"west": {"uv": [31.06, 14.06], "uv_size": [0.88, 0.88]},
								"up": {"uv": [31.06, 15.06], "uv_size": [0.88, 0.88]},
								"down": {"uv": [31.06, 16.94], "uv_size": [0.88, -0.88]}
							}
						},
						{
							"origin": [-2.22889, -3.71886, -6.61385],
							"size": [1, 0.8, 1.3],
							"pivot": [0, 0, 0],
							"rotation": [-42.6984, 32.8365, 22.58957],
							"uv": {
								"north": {"uv": [31.06, 17.06], "uv_size": [0.88, 0.88]},
								"east": {"uv": [26.06, 9.06], "uv_size": [1.44, 0.88]},
								"south": {"uv": [31.06, 18.06], "uv_size": [0.88, 0.88]},
								"west": {"uv": [10.06, 30.06], "uv_size": [1.44, 0.88]},
								"up": {"uv": [11.06, 24.06], "uv_size": [0.88, 1.44]},
								"down": {"uv": [24.06, 31.5], "uv_size": [0.88, -1.44]}
							}
						},
						{
							"origin": [-2.72889, -4.31886, -7.21385],
							"size": [2, 2, 0.6],
							"pivot": [0, 0, 0],
							"rotation": [-42.6984, 32.8365, 22.58957],
							"uv": {
								"north": {"uv": [10.06, 28.06], "uv_size": [1.88, 1.88]},
								"east": {"uv": [31.06, 19.06], "uv_size": [0.44, 1.88]},
								"south": {"uv": [24.06, 28.06], "uv_size": [1.88, 1.88]},
								"west": {"uv": [31.06, 21.06], "uv_size": [0.44, 1.88]},
								"up": {"uv": [31.06, 23.06], "uv_size": [1.88, 0.44]},
								"down": {"uv": [31.06, 24.5], "uv_size": [1.88, -0.44]}
							}
						},
						{
							"origin": [2.40457, -3.71886, -5.38277],
							"size": [1, 0.8, 1.3],
							"pivot": [0, 0, 0],
							"rotation": [-110.81988, 52.44, -66.4566],
							"uv": {
								"north": {"uv": [28.06, 31.06], "uv_size": [0.88, 0.88]},
								"east": {"uv": [25.06, 30.06], "uv_size": [1.44, 0.88]},
								"south": {"uv": [31.06, 28.06], "uv_size": [0.88, 0.88]},
								"west": {"uv": [30.06, 26.06], "uv_size": [1.44, 0.88]},
								"up": {"uv": [27.06, 30.06], "uv_size": [0.88, 1.44]},
								"down": {"uv": [30.06, 28.5], "uv_size": [0.88, -1.44]}
							}
						},
						{
							"origin": [1.90457, -4.31886, -5.98277],
							"size": [2, 2, 0.6],
							"pivot": [0, 0, 0],
							"rotation": [-110.81988, 52.44, -66.4566],
							"uv": {
								"north": {"uv": [26.06, 28.06], "uv_size": [1.88, 1.88]},
								"east": {"uv": [25.06, 31.06], "uv_size": [0.44, 1.88]},
								"south": {"uv": [28.06, 26.06], "uv_size": [1.88, 1.88]},
								"west": {"uv": [26.06, 31.06], "uv_size": [0.44, 1.88]},
								"up": {"uv": [31.06, 25.06], "uv_size": [1.88, 0.44]},
								"down": {"uv": [31.06, 27.5], "uv_size": [1.88, -0.44]}
							}
						},
						{
							"origin": [-0.87663, -5.41218, -7.37274],
							"size": [2, 1.8, 0.5],
							"pivot": [0, 0, 0],
							"rotation": [-75, 47.5, 0],
							"uv": {
								"north": {"uv": [8.06, 28.06], "uv_size": [1.88, 1.88]},
								"east": {"uv": [6.06, 31.06], "uv_size": [0.44, 1.88]},
								"south": {"uv": [28.06, 8.06], "uv_size": [1.88, 1.88]},
								"west": {"uv": [7.06, 31.06], "uv_size": [0.44, 1.88]},
								"up": {"uv": [10.06, 31.06], "uv_size": [1.88, 0.44]},
								"down": {"uv": [31.06, 10.5], "uv_size": [1.88, -0.44]}
							}
						},
						{
							"origin": [-1.12337, -1.826, -6.81871],
							"size": [2, 9.8, 2],
							"pivot": [0, 0, 0],
							"rotation": [-20, -47.5, 0],
							"uv": {
								"north": {"uv": [20.06, 12.06], "uv_size": [1.88, 9.88]},
								"east": {"uv": [12.06, 22.06], "uv_size": [1.88, 9.88]},
								"south": {"uv": [22.06, 12.06], "uv_size": [1.88, 9.88]},
								"west": {"uv": [14.06, 22.06], "uv_size": [1.88, 9.88]},
								"up": {"uv": [10.06, 26.06], "uv_size": [1.88, 1.88]},
								"down": {"uv": [24.06, 27.94], "uv_size": [1.88, -1.88]}
							}
						},
						{
							"origin": [-1.12337, -1.826, 4.81871],
							"size": [2, 9.8, 2],
							"pivot": [0, 0, 0],
							"rotation": [20, 47.5, 0],
							"uv": {
								"north": {"uv": [16.06, 22.06], "uv_size": [1.88, 9.88]},
								"east": {"uv": [18.06, 22.06], "uv_size": [1.88, 9.88]},
								"south": {"uv": [20.06, 22.06], "uv_size": [1.88, 9.88]},
								"west": {"uv": [22.06, 22.06], "uv_size": [1.88, 9.88]},
								"up": {"uv": [26.06, 26.06], "uv_size": [1.88, 1.88]},
								"down": {"uv": [28.06, 3.94], "uv_size": [1.88, -1.88]}
							}
						},
						{
							"origin": [-0.87663, -1.826, 4.81871],
							"size": [2, 9.8, 2],
							"pivot": [0, 0, 0],
							"rotation": [20, -47.5, 0],
							"uv": {
								"north": {"uv": [0.06, 24.06], "uv_size": [1.88, 9.88]},
								"east": {"uv": [24.06, 0.06], "uv_size": [1.88, 9.88]},
								"south": {"uv": [2.06, 24.06], "uv_size": [1.88, 9.88]},
								"west": {"uv": [4.06, 24.06], "uv_size": [1.88, 9.88]},
								"up": {"uv": [28.06, 4.06], "uv_size": [1.88, 1.88]},
								"down": {"uv": [28.06, 7.94], "uv_size": [1.88, -1.88]}
							}
						}
					]
				}
			]
		}
	]
}